exp_selection/__init__.py
exp_selection/cli.py
exp_selection/compute.py
exp_selection/plot.py
exp_selection/prepare.py
exp_selection/preprocessing.py
exp_selection/rank_tools.py
exp_selection/utils.py
exp_selection/xp_utils.py
exp_selection/xpehh.py
exp_selection-1.0.0.dist-info/LICENSE
exp_selection-1.0.0.dist-info/METADATA
exp_selection-1.0.0.dist-info/WHEEL
exp_selection-1.0.0.dist-info/entry_points.txt
exp_selection-1.0.0.dist-info/top_level.txt
exp_selection-1.0.0.dist-info/RECORD
