Metadata-Version: 2.1
Name: exp-selection
Version: 1.0.0
Summary: UNKNOWN
Home-page: https://github.com/ondra-m/exp-selection
Author: Ondřej Moravčík
License: UNKNOWN
Project-URL: Bug Tracker, https://github.com/ondra-m/exp-selection/issues
Platform: UNKNOWN
Classifier: Programming Language :: Python :: 3
Classifier: License :: OSI Approved :: MIT License
Classifier: Operating System :: OS Independent
Classifier: Topic :: Scientific/Engineering :: Bio-Informatics
Requires-Python: >=3.8
License-File: LICENSE
Requires-Dist: scikit-allel
Requires-Dist: zarr
Requires-Dist: argparse
Requires-Dist: numpy
Requires-Dist: pandas
Requires-Dist: matplotlib
Requires-Dist: seaborn
